{
    "$schema": "https://vega.github.io/schema/vega-lite/v5.json",
    "description": "SAS litter",
    "title": {
        "text": "Relating Population and Happiness Levels in 2021",
        "subtitle": "Source: World Population Review",
        "subtitleFontStyle": "italic",
        "subtitleFontSize": 10,
        "anchor": "start",
        "color": "black"
    },

    "data": {
        "url": "https://raw.githubusercontent.com/jamesaubs/jamesaubs.github.io/main/happydata.csv"
    },
    "mark": {
        "type": "bar",
        "color": "#9cd84ed8",
        "strokeWidth": 2,
        "opacity": 1
    },
    "height": 300,
    "width": 350,
    "encoding": {
        "y": {
            "field": "country",
            "type": "ordinal",
            "sort": [],
            "title": null
        },
        "x": {
            "field": "pop2021",
            "type": "quantitative",
            "title": "Population '000s"
        },
        "tooltip": [
            {
                "field": "rank",
                "type": "quantitative",
                "title": "Rank"
            },
            {
                "field": "happiness2020",
                "type": "quantitative",
                "title": "Happiness Value 2020"
            }
        ]
    }
}
